fastapi_simple_jwt/__init__.py
fastapi_simple_jwt/match_login.py
fastapi_simple_jwt/simple_jwt.py
fastapi_simple_jwt-0.1.1.dist-info/LICENSE
fastapi_simple_jwt-0.1.1.dist-info/METADATA
fastapi_simple_jwt-0.1.1.dist-info/WHEEL
fastapi_simple_jwt-0.1.1.dist-info/top_level.txt
fastapi_simple_jwt-0.1.1.dist-info/RECORD
