Metadata-Version: 2.1
Name: fastapi-simple-jwt
Version: 0.1.1
Summary: A simple FastAPIJWT verification module
Home-page: https://github.com/Thresh-Frazier/fastapi-simple-jwt
Author: Frazier
Author-email: 470664041@qq.com
License: MIT
Classifier: License :: OSI Approved :: MIT License
Classifier: Programming Language :: Python
Classifier: Programming Language :: Python :: 3
Classifier: Programming Language :: Python :: 3.6
Classifier: Programming Language :: Python :: Implementation :: CPython
Classifier: Programming Language :: Python :: Implementation :: PyPy
Requires-Python: >=3.6.0
License-File: LICENSE
Requires-Dist: fastapi
Requires-Dist: passlib
Requires-Dist: pydantic
Requires-Dist: pydantic-settings
Requires-Dist: python-jose
